jupyter_slurm_provisioner/__init__.py
jupyter_slurm_provisioner/__main__.py
jupyter_slurm_provisioner/provisioner.py
jupyter_slurm_provisioner-0.6.0.data/scripts/slurm_watch
jupyter_slurm_provisioner-0.6.0.dist-info/LICENSE
jupyter_slurm_provisioner-0.6.0.dist-info/METADATA
jupyter_slurm_provisioner-0.6.0.dist-info/WHEEL
jupyter_slurm_provisioner-0.6.0.dist-info/entry_points.txt
jupyter_slurm_provisioner-0.6.0.dist-info/top_level.txt
jupyter_slurm_provisioner-0.6.0.dist-info/RECORD
