Metadata-Version: 2.1
Name: jupyter-slurm-provisioner
Version: 0.6.0
Summary: Jupyter slurm kernel provisioner
Home-page: https://github.com/FZJ-JSC/jupyter-slurm-provisioner
Author: Tim Kreuzer
Author-email: t.kreuzer@fz-juelich.de
License: MIT
License-File: LICENSE
Requires-Dist: jupyter-client (>=7.1.2)
